{
  "knownName": "صخر بن جويرية",
  "teachers": [
    {
      "name": "حميد بن نافع المدني",
      "symbols": ""
    },
    {
      "name": "عامر بن عَبد الله بن الزبير بن العوام",
      "symbols": ""
    },
    {
      "name": "عبد الرحمن بن القاسم بْن مُحَمَّد بْن أَبي بكر الصديق",
      "symbols": "(خ)"
    },
    {
      "name": "نافع مولى ابْن عُمَر",
      "symbols": "(خ م د ت)"
    },
    {
      "name": "هشام بْن عروة",
      "symbols": "(ت)"
    },
    {
      "name": "أبي جاء العطاردي",
      "symbols": "(س)"
    },
    {
      "name": "عائشة بنت سعد بْن أَبي وقاص",
      "symbols": ""
    }
  ],
  "students": [
    {
      "name": "إسماعيل بن علية",
      "symbols": "(ت)"
    },
    {
      "name": "أيوب السختياني",
      "symbols": ""
    },
    {
      "name": "بشر بْن السري",
      "symbols": ""
    },
    {
      "name": "بشر بن عُمَر الزهراني",
      "symbols": ""
    },
    {
      "name": "بشر بن المفضل",
      "symbols": "(م)"
    },
    {
      "name": "حماد بن زيد",
      "symbols": "(ت)"
    },
    {
      "name": "داود بن الزبرقان",
      "symbols": ""
    },
    {
      "name": "روح بْن عبادة",
      "symbols": "(م)"
    },
    {
      "name": "سَعِيد بن عامر الضبيعي",
      "symbols": ""
    },
    {
      "name": "أبو قُتَيبة سَلْم بْن قتيبة",
      "symbols": ""
    },
    {
      "name": "أَبُو داود سُلَيْمان بْن داود الطيالسي",
      "symbols": ""
    },
    {
      "name": "أبو بدر شجاع بْن الوليد",
      "symbols": ""
    },
    {
      "name": "شعيب بن حرب المدائني",
      "symbols": "(خ)"
    },
    {
      "name": "عبد الله بْن المبارك",
      "symbols": ""
    },
    {
      "name": "عبد الرحمن بن مهدي",
      "symbols": "(د)"
    },
    {
      "name": "عبد الوهاب بْن عطاء",
      "symbols": ""
    },
    {
      "name": "عُبَيد اللَّه بْن تمام",
      "symbols": ""
    },
    {
      "name": "عثمان بن عُمَر بن فارس",
      "symbols": ""
    },
    {
      "name": "عثمان بن مطر",
      "symbols": ""
    },
    {
      "name": "عفان بن مسلم",
      "symbols": "(خ م)"
    },
    {
      "name": "علي بْن الجعد",
      "symbols": ""
    },
    {
      "name": "علي بن نصر الجهضمي الأكبر",
      "symbols": "(م)"
    },
    {
      "name": "عَمْرو بن عاصم الكِلابي",
      "symbols": ""
    },
    {
      "name": "أبو نعيم الفضل بْن دكين",
      "symbols": "(خ)"
    },
    {
      "name": "محمد بْن عبد الرحمن الطفاوي",
      "symbols": ""
    },
    {
      "name": "مسلم بن إبراهيم",
      "symbols": ""
    },
    {
      "name": "المعافى بن عِمْران الموصلي",
      "symbols": "(س)"
    },
    {
      "name": "النضر بن عاصم بن هلال البارقي",
      "symbols": ""
    },
    {
      "name": "النضر بن محمد الجرشي",
      "symbols": "(خ)"
    },
    {
      "name": "أبو الوليد هشام بْن عَبد المَلِك الطيالسي",
      "symbols": ""
    },
    {
      "name": "وهب بْن جرير بْن حازم",
      "symbols": "(خ)"
    },
    {
      "name": "يحيى بْن سَعِيد القطان",
      "symbols": ""
    },
    {
      "name": "يزيد بْن زريع",
      "symbols": ""
    },
    {
      "name": "يزيد بْن هارون",
      "symbols": ""
    },
    {
      "name": "يعقوب بْن إسحاق الحضرمي",
      "symbols": ""
    },
    {
      "name": "أبو سَعِيد مولى بني هاشم",
      "symbols": "(خ)"
    },
    {
      "name": "أبو عَمْرو بن العلاء المقرئ",
      "symbols": ""
    }
  ]
}