{
  "knownName": "المطرف",
  "teachers": [
    {
      "name": "الحسين بن عَلِي بْن أَبي طَالِب",
      "symbols": ""
    },
    {
      "name": "خارجة بْن زَيْد بْن ثَابِت",
      "symbols": "(ت)"
    },
    {
      "name": "رافع بن خديج",
      "symbols": "(م)"
    },
    {
      "name": "عَبْد الله بْن عباس",
      "symbols": ""
    },
    {
      "name": "عبد الله بْن عُمَر بْن الخطاب",
      "symbols": ""
    },
    {
      "name": "عبد الرحمن بْن أَبي عَمْرة",
      "symbols": "(م د ت كن)"
    },
    {
      "name": "أبيه عَمْرو بن عثمان بن عفان",
      "symbols": ""
    },
    {
      "name": "أبي حبة البدري المازني",
      "symbols": ""
    },
    {
      "name": "أبي عُمَرة",
      "symbols": "(ت س)"
    }
  ],
  "students": [
    {
      "name": "ابنه مُحَمَّد بْن عَبد اللَّهِ بْن عَمْرو بْن عثمان بْن عفان المعروف بالديباج",
      "symbols": ""
    },
    {
      "name": "محمد بْن عَبْد الرَّحْمَنِ بْن أَبي لبيبة",
      "symbols": ""
    },
    {
      "name": "محمد بن مسلم بْن شهاب الزُّهْرِيّ",
      "symbols": ""
    },
    {
      "name": "محمد بْن يُوسُفَ الكندي",
      "symbols": ""
    },
    {
      "name": "هشام بن سَعْدٍ",
      "symbols": ""
    },
    {
      "name": "أبو بكر بْن مُحَمَّد بْن عَمْرو بن حزم",
      "symbols": "(م د ت س)"
    }
  ]
}