{
  "knownName": "عبد الله بن مسلم بن جندب",
  "teachers": [
    {
      "name": "عِيسَى بْن طلحة بْن عُبَيد اللَّه",
      "symbols": ""
    },
    {
      "name": "أبيه مسلم بْن جندب",
      "symbols": "(ت)"
    }
  ],
  "students": [
    {
      "name": "مُحَمَّدِ بْنِ إسماعيل بْن أَبي فديك",
      "symbols": "(ت)"
    },
    {
      "name": "مُحَمَّد بْن طلحة التَّيْمِيّ",
      "symbols": ""
    },
    {
      "name": "أَبُو مروان مُحَمَّد بْن عُثْمَان بْن خالد العثماني",
      "symbols": ""
    }
  ]
}