{
  "knownName": "أبو الوزير المروزي",
  "teachers": [
    {
      "name": "سُفْيَان بْن عُيَيْنَة",
      "symbols": ""
    },
    {
      "name": "عبد الله بْن المبارك",
      "symbols": "(ل ت)"
    },
    {
      "name": "عبد الرحمن بْن مهدي",
      "symbols": ""
    },
    {
      "name": "فضيل بْن عِيَاض",
      "symbols": ""
    },
    {
      "name": "النضر بْن مُحَمَّد الْمَرْوَزِيّ",
      "symbols": "(ل)"
    },
    {
      "name": "أَبِي الْحَجَّاج الزاهد",
      "symbols": ""
    }
  ],
  "students": [
    {
      "name": "أَحْمَد بن حنبل",
      "symbols": ""
    },
    {
      "name": "أحمد بن سَعِيد الدارمي",
      "symbols": ""
    },
    {
      "name": "أَحْمَد بْن عبدة الآملي",
      "symbols": "(ت)"
    },
    {
      "name": "أَحْمَد بْن علي بْن الجنيد",
      "symbols": ""
    },
    {
      "name": "أَحْمَد بْن مَنْصُور زاج الْمَرْوَزِيّ",
      "symbols": ""
    },
    {
      "name": "إسحاق بْن راهويه",
      "symbols": ""
    },
    {
      "name": "عبد اللَّهِ بْن أَحْمَد بْن شبويه",
      "symbols": ""
    },
    {
      "name": "عبدة بْن عَبد الرحيم المروزي",
      "symbols": ""
    },
    {
      "name": "أَبُو عُمَر عُبَيد بْن مُوسَى البَصْرِيّ ثُمَّ النسفي",
      "symbols": ""
    },
    {
      "name": "علي بْن خشرم",
      "symbols": ""
    },
    {
      "name": "محمد بن إبراهيم ابن يوسف",
      "symbols": ""
    },
    {
      "name": "مُحَمَّد بْن عَبد اللَّهِ بْن قهزاذ",
      "symbols": ""
    },
    {
      "name": "مُحَمَّد بْن عبد العزيز ابن أَبي رزمة",
      "symbols": "(ل)"
    },
    {
      "name": "مُحَمَّد بْن علي بْن الْحَسَن بْن شقيق",
      "symbols": ""
    },
    {
      "name": "النضر ابن سلمة شَاذَانَ",
      "symbols": ""
    },
    {
      "name": "هارون بْن إِسْحَاق الهمداني الكوفي",
      "symbols": ""
    }
  ]
}