{
  "knownName": "أسيد بن زيد الجمال",
  "teachers": [
    {
      "name": "أبي إسرائيل إِسْمَاعِيل بْن خليفة الملائي",
      "symbols": ""
    },
    {
      "name": "جعفر بْن زياد الأحمر",
      "symbols": ""
    },
    {
      "name": "الحسن بْن صَالِح بْن حي",
      "symbols": ""
    },
    {
      "name": "حلو بْن السري الأَودِيّ",
      "symbols": ""
    },
    {
      "name": "زهير بْن مُعَاوِيَة",
      "symbols": ""
    },
    {
      "name": "شَرِيك بْن عَبد اللَّهِ النَّخَعِيّ",
      "symbols": ""
    },
    {
      "name": "طعمة بْن عَمْرو الجعفري",
      "symbols": ""
    },
    {
      "name": "عَبد اللَّه بْن المبارك",
      "symbols": ""
    },
    {
      "name": "أبي مريم عبد الغفار بْن القاسم الأَنْصارِيّ",
      "symbols": ""
    },
    {
      "name": "عَمْرو بْن أَبي المقدام ثَابِت بْن هرمز",
      "symbols": ""
    },
    {
      "name": "عَمْرو بن شمرالْجُعْفِيّ",
      "symbols": ""
    },
    {
      "name": "قيس بْن الربيع",
      "symbols": ""
    },
    {
      "name": "الليث بْن سعد",
      "symbols": ""
    },
    {
      "name": "محمد بْن طلحة بْن مصرف",
      "symbols": ""
    },
    {
      "name": "محمد بْن عطية بْن سعد العوفي",
      "symbols": ""
    },
    {
      "name": "محمد بْن عَمْرو بْن عُبَيد الأَنْصارِيّ الواقفي",
      "symbols": ""
    },
    {
      "name": "محمد بْن الفضل بْن عطية الخراساني",
      "symbols": ""
    },
    {
      "name": "منصور ابن أَبي الأسود",
      "symbols": ""
    },
    {
      "name": "هريم بْن سفيان",
      "symbols": ""
    },
    {
      "name": "هشيم بْن بشير",
      "symbols": "(خ)"
    },
    {
      "name": "أبي المحياة يَحْيَى بْن يَعْلَى التَّيْمِيّ",
      "symbols": ""
    },
    {
      "name": "أبي بَكْر بْن عياش",
      "symbols": ""
    }
  ],
  "students": [
    {
      "name": "البخاري",
      "symbols": ""
    },
    {
      "name": "إبراهيم بْن إِسْحَاق الحربي",
      "symbols": ""
    },
    {
      "name": "إبراهيم بْن راشد الأدمي",
      "symbols": ""
    },
    {
      "name": "أحمد بْن آدم غندر",
      "symbols": ""
    },
    {
      "name": "أبو جعفر أَحْمَد بْن علي بْن الفضيل الخزاز الْمُقْرِئ",
      "symbols": ""
    },
    {
      "name": "أبو الحسين أَحْمَد بْن مُحَمَّد بْن يحيى بْن عَمْرو الجعفري الخازمي الكوفي",
      "symbols": ""
    },
    {
      "name": "أحمد بْن يَحْيَى بْن زَكَرِيَّا الصوفي",
      "symbols": ""
    },
    {
      "name": "إسماعيل بْن عَبد اللَّهِ الأصبهاني سمويه",
      "symbols": ""
    },
    {
      "name": "أبو صالح حامد بْن دَاوُد الشاشي",
      "symbols": ""
    },
    {
      "name": "الحسن بْن علي بْن عفان العامري",
      "symbols": ""
    },
    {
      "name": "الحسن بْن مُعَاوِيَة بْن هشام",
      "symbols": ""
    },
    {
      "name": "الحكم بْن عَمْرو الأَنْمَاطِيّ",
      "symbols": ""
    },
    {
      "name": "أبو بدر عباد بْن الوليد الغبري",
      "symbols": ""
    },
    {
      "name": "عبد اللَّه بْن عُمَر بْن أبان مشكدانة",
      "symbols": ""
    },
    {
      "name": "علي بْن سهل بْن المغيرة النَّسَائي البزار",
      "symbols": ""
    },
    {
      "name": "عُمَر بْن حفص بْن عُمَر بْن راشد الربعي الشطوي عم محمد بن جعفر ابن الإمام الدمياطي",
      "symbols": ""
    },
    {
      "name": "عيسى بْن عَبد اللَّهِ الطيالسي زغاث",
      "symbols": ""
    },
    {
      "name": "القاسم بْن مُحَمَّد بْن حماد الدلال الكوفي",
      "symbols": ""
    },
    {
      "name": "أَبُو أمية مُحَمَّد بْن إِبْرَاهِيم الطرسوسي",
      "symbols": ""
    },
    {
      "name": "محمد بْن شعبة بْن جوان البَصْرِيّ",
      "symbols": ""
    },
    {
      "name": "محمد بْن عُبَيد بْن عتبة الكندي",
      "symbols": ""
    },
    {
      "name": "أبو كريب محمد بن العلاء",
      "symbols": ""
    },
    {
      "name": "محمد ابن مروان الكوفي",
      "symbols": ""
    },
    {
      "name": "محمد بْن مسلم بْن وارة الرازي",
      "symbols": ""
    },
    {
      "name": "هارون بْن سفيان المستملي",
      "symbols": ""
    }
  ]
}