{
  "knownName": "محمد بن يوسف بن عبد الله بن سلام",
  "teachers": [
    {
      "name": "عَبد اللَّهِ بْن الزبير",
      "symbols": ""
    },
    {
      "name": "يوسف بْن عَبد الله بْن سلام",
      "symbols": "(ت)"
    },
    {
      "name": "أبي سَعِيد الخُدْرِيّ",
      "symbols": ""
    }
  ],
  "students": [
    {
      "name": "شعيب بْن صفوان الثقفي",
      "symbols": ""
    },
    {
      "name": "شهر بْن حوشب",
      "symbols": ""
    },
    {
      "name": "عبد الملك بْن عُمَير",
      "symbols": ""
    },
    {
      "name": "عثمان بْن الضحاك",
      "symbols": "(ت)"
    },
    {
      "name": "عَمْرو بْن يحيى بْن عمارة",
      "symbols": ""
    },
    {
      "name": "محمد بْن عجلان",
      "symbols": ""
    },
    {
      "name": "أبو الورد شيخ لإِسماعيل ابن داود المخراقي",
      "symbols": ""
    }
  ]
}