{
  "knownName": "عليلة",
  "teachers": [
    {
      "name": "أيوب السختياني",
      "symbols": ""
    },
    {
      "name": "أبيه بدر بْن عَمْرو السعدي",
      "symbols": "(ق)"
    },
    {
      "name": "خالد الحذاء",
      "symbols": ""
    },
    {
      "name": "راشد أبي مُحَمَّد الحماني",
      "symbols": ""
    },
    {
      "name": "سَعِيد الجريري",
      "symbols": "(ق)"
    },
    {
      "name": "سُلَيْمان الأعمش",
      "symbols": ""
    },
    {
      "name": "عبد الله بْن زياد بْن سمعان",
      "symbols": ""
    },
    {
      "name": "عبد الملك بْن عبد العزيز بْن جُرَيْج",
      "symbols": ""
    },
    {
      "name": "عُبَيد الله بْن حيان",
      "symbols": ""
    },
    {
      "name": "علي بْن زيد بْن جدعان",
      "symbols": ""
    },
    {
      "name": "عنظوانة السعدي البَصْرِيّ",
      "symbols": ""
    },
    {
      "name": "عوف الأعرابي",
      "symbols": ""
    },
    {
      "name": "النهاس بْن قهم",
      "symbols": ""
    },
    {
      "name": "هارون بْن رئاب",
      "symbols": ""
    },
    {
      "name": "يونس بْن عُبَيد",
      "symbols": ""
    },
    {
      "name": "أبي الأشهب العطاردي",
      "symbols": "(ت)"
    },
    {
      "name": "أبي الزبير المكي",
      "symbols": "(ق)"
    },
    {
      "name": "أبي هارون العبدي",
      "symbols": ""
    }
  ],
  "students": [
    {
      "name": "إبراهيم بْن لقين",
      "symbols": ""
    },
    {
      "name": "أحمد بْن أَبي طيبة الجرجاني",
      "symbols": ""
    },
    {
      "name": "أَحْمَد بن عُبَيد الله الغداني",
      "symbols": ""
    },
    {
      "name": "أحمد بْن أَبي نافع الموصلي",
      "symbols": ""
    },
    {
      "name": "آدم بْن أَبي إياس",
      "symbols": ""
    },
    {
      "name": "إسحاق بْن أَبي إسرائيل",
      "symbols": ""
    },
    {
      "name": "إسحاق بْن منصور السلولي",
      "symbols": ""
    },
    {
      "name": "أبو معمر إسماعيل بن إبراهيم بْن إبراهيم الهذلي",
      "symbols": ""
    },
    {
      "name": "داهر بْن نوح",
      "symbols": ""
    },
    {
      "name": "داود بْن رشيد",
      "symbols": ""
    },
    {
      "name": "أبو توبة الربيع بْن نَافِع الحلبي",
      "symbols": ""
    },
    {
      "name": "سُلَيْمان بْن داود الشاذكوني",
      "symbols": ""
    },
    {
      "name": "سهل بْن عثمان العسكري",
      "symbols": ""
    },
    {
      "name": "صالح بْن عَبد الله التِّرْمِذِيّ",
      "symbols": ""
    },
    {
      "name": "صالح بْن مُحَمَّد التِّرْمِذِيّ",
      "symbols": ""
    },
    {
      "name": "العباس بْن سليم الموصلي",
      "symbols": ""
    },
    {
      "name": "عبد الله بْن الجراح القهستاني",
      "symbols": ""
    },
    {
      "name": "عبد الله بْن رشيد العتكي",
      "symbols": ""
    },
    {
      "name": "عبد الله بْن عون",
      "symbols": ""
    },
    {
      "name": "عبد الله بْن معاوية الجمحي",
      "symbols": ""
    },
    {
      "name": "عبد الرحمن بْن واقد الواقدي",
      "symbols": ""
    },
    {
      "name": "عبد السلام بْن عُمَر الجني",
      "symbols": ""
    },
    {
      "name": "عبد الصمد بْن عبد العزيز الرازي",
      "symbols": ""
    },
    {
      "name": "علي بْن حجر السعدي",
      "symbols": "(ت)"
    },
    {
      "name": "عَمْرو بْن خالد الحراني",
      "symbols": ""
    },
    {
      "name": "الفضل بْن غانم البغدادي",
      "symbols": ""
    },
    {
      "name": "الفضل بْن موسى السيناني",
      "symbols": ""
    },
    {
      "name": "أبو كامل فضيل بْن حسين الجحدري",
      "symbols": ""
    },
    {
      "name": "قتيبة بْن سَعِيد",
      "symbols": ""
    },
    {
      "name": "قيس بْن حفص",
      "symbols": ""
    },
    {
      "name": "كثير بْن شيبان",
      "symbols": ""
    },
    {
      "name": "مُحَمَّد بْن خالد الحنظلي الرازي",
      "symbols": ""
    },
    {
      "name": "مُحَمَّد بْن سُلَيْمان لوين",
      "symbols": ""
    },
    {
      "name": "مُحَمَّد بْن عيسى ابن الطباع",
      "symbols": ""
    },
    {
      "name": "مكي بْن إبراهيم البلخي",
      "symbols": ""
    },
    {
      "name": "مهدي بْن عيسى الواسطي",
      "symbols": ""
    },
    {
      "name": "هشام بن عمار الدمشقي",
      "symbols": "(ق)"
    },
    {
      "name": "يحيى بْن إسحاق السيلحيني",
      "symbols": ""
    },
    {
      "name": "يحيى بْن أَبي بُكَيْر الكرماني",
      "symbols": ""
    },
    {
      "name": "يحيى بْن عبد الحميد الحماني",
      "symbols": ""
    },
    {
      "name": "يزيد بْن عُمَر بْن جبره",
      "symbols": ""
    },
    {
      "name": "يزيد بْن هارون",
      "symbols": ""
    },
    {
      "name": "أبو يوسف يعقوب بْن إبراهيم الكوفي",
      "symbols": ""
    }
  ]
}