{
  "knownName": "زهرة بن معبد",
  "teachers": [
    {
      "name": "الحارث مولى عثمان بْن عفان",
      "symbols": ""
    },
    {
      "name": "سَعِيد بْن المُسَيَّب",
      "symbols": ""
    },
    {
      "name": "عبد الله بْن الزبير",
      "symbols": "(خ)"
    },
    {
      "name": "عبد الله بْن السائب",
      "symbols": ""
    },
    {
      "name": "عبد الله بْن عُمَر بْن الخطاب",
      "symbols": "(خ)"
    },
    {
      "name": "جده عَبد الله بْن هشام",
      "symbols": "(خ د)"
    },
    {
      "name": "عبد الله بْن يزيد أَبِي عَبْد الرَّحْمَنِ الحبلي",
      "symbols": "(د س)"
    },
    {
      "name": "عبد الرحمن بْن حجيرة",
      "symbols": ""
    },
    {
      "name": "عُمَر بْن عبد العزيز",
      "symbols": ""
    },
    {
      "name": "أبيه معبد بْن عَبد الله بْن هشام",
      "symbols": "(ق)"
    },
    {
      "name": "أبي صالح مولى عثمان بْن عفان",
      "symbols": "(ت س)"
    },
    {
      "name": "أبي عُبَيدة بْن عقبة بْن نافع",
      "symbols": ""
    },
    {
      "name": "ابْن عمه ولم يسمه",
      "symbols": "(د س)"
    }
  ],
  "students": [
    {
      "name": "حيوة بْن شريح",
      "symbols": "(خ س ق)"
    },
    {
      "name": "خالد بْن حميد المهري",
      "symbols": ""
    },
    {
      "name": "رشدين بْن سعد",
      "symbols": ""
    },
    {
      "name": "سَعِيد بْن أَبي أيوب",
      "symbols": "(خ د س)"
    },
    {
      "name": "عاصم بْن عَبد الله بن جابر",
      "symbols": ""
    },
    {
      "name": "عَبْد اللَّهِ بن لَهِيعَة",
      "symbols": ""
    },
    {
      "name": "الليث بْن سعد",
      "symbols": "(ت س ق)"
    },
    {
      "name": "نافع بْن يزيد",
      "symbols": ""
    },
    {
      "name": "أبو السمح",
      "symbols": ""
    },
    {
      "name": "أبو معن",
      "symbols": "(س)"
    }
  ]
}