{
  "knownName": "سعد بن أوس العبسي",
  "teachers": [
    {
      "name": "بلال بْن يَحْيَى الْعَبْسِيّ",
      "symbols": "(بخ ٤)"
    },
    {
      "name": "عامر الشعبي",
      "symbols": ""
    }
  ],
  "students": [
    {
      "name": "سُفْيَان بْن عُقْبَة",
      "symbols": ""
    },
    {
      "name": "عُبَيد الله بْن موسى",
      "symbols": "(ق)"
    },
    {
      "name": "علي بْن غراب",
      "symbols": ""
    },
    {
      "name": "أَبُو نُعَيْم الْفَضْل بْن دكين",
      "symbols": "(س)"
    },
    {
      "name": "أَبُو أَحْمَد مُحَمَّد بْن عَبد اللَّهِ بْن الزبير الزبيري",
      "symbols": "(د ت)"
    },
    {
      "name": "وكيع بْن الجراح",
      "symbols": "(بخ د س)"
    }
  ]
}