{
  "knownName": "شَيْبَة بن عُثْمَانَ",
  "teachers": [
    {
      "name": "النَّبِيّ صَلَّى اللَّهُ عَلَيْهِ وسَلَّمَ",
      "symbols": ""
    },
    {
      "name": "أبي بَكْر الصديقعَبد الله بْن أَبي قحافة",
      "symbols": ""
    },
    {
      "name": "ابن عمه عُثْمَان بْن طلحة بْن أَبي طلحة الحجبي",
      "symbols": ""
    },
    {
      "name": "عُمَر بْن الخطاب",
      "symbols": "(خ د ق)"
    }
  ],
  "students": [
    {
      "name": "أَبُو وائل شقيق بْنُ سَلَمَةَ الأَسَدِيُّ",
      "symbols": "(خ د ق)"
    },
    {
      "name": "عَبْدُ الرَّحْمَنِ بْنُ الزَّجَّاجِ",
      "symbols": ""
    },
    {
      "name": "عِكْرِمَةُ مَوْلَى ابْنِ عَبَّاسٍ",
      "symbols": ""
    },
    {
      "name": "ابْنُ ابْنِهِ مُسَافِعُ بْنُ عَبد اللَّهِ بْنِ شَيْبَة",
      "symbols": ""
    },
    {
      "name": "ابْنُهُ مُصْعَبُ بْنُ شَيْبَة",
      "symbols": ""
    }
  ]
}