{
  "knownName": "شريح بن عبيد الحضرمي",
  "teachers": [
    {
      "name": "أيوب بْن عَبد اللَّهِ بْن مكرز",
      "symbols": ""
    },
    {
      "name": "بشير بْن عقربة الجهني",
      "symbols": ""
    },
    {
      "name": "ثوبان مولى رَسُول اللَّهِ صلى الله عليه وسلم",
      "symbols": ""
    },
    {
      "name": "جبير بْن نفير",
      "symbols": "(د)"
    },
    {
      "name": "الحارث بْن الحارث العامدي",
      "symbols": ""
    },
    {
      "name": "حبيب بْن عُبَيد",
      "symbols": ""
    },
    {
      "name": "خداش",
      "symbols": ""
    },
    {
      "name": "الزبير بْن الْوَلِيد",
      "symbols": "(د سي)"
    },
    {
      "name": "سعد بْن أَبي وقاص",
      "symbols": "(د)"
    },
    {
      "name": "شراحيل بْن معشر العنسي",
      "symbols": ""
    },
    {
      "name": "شُرَحْبِيل بْن السِّمْط",
      "symbols": ""
    },
    {
      "name": "أَبِي أُمَامَة صدي بْن عجلان الباهلي",
      "symbols": "(د)"
    },
    {
      "name": "الصعب بْن جثامة الليثي",
      "symbols": ""
    },
    {
      "name": "ظبيان الشامي",
      "symbols": ""
    },
    {
      "name": "أَبِي بحرية عَبد الله بْن قيس التراغمي",
      "symbols": ""
    },
    {
      "name": "عَبْد الرحمن بْن سلامة",
      "symbols": ""
    },
    {
      "name": "عبد الرحمن بن عائذ الأزدي",
      "symbols": "(س)"
    },
    {
      "name": "عتبة بْن عَبْد السلمي",
      "symbols": ""
    },
    {
      "name": "العرباض بْن سارية",
      "symbols": ""
    },
    {
      "name": "عقبة بْن عامر الجهني",
      "symbols": ""
    },
    {
      "name": "عَمْرو بْن الأسود",
      "symbols": "(د)"
    },
    {
      "name": "فضالة بْن عُبَيد",
      "symbols": ""
    },
    {
      "name": "قزعة بْن يَحْيَى",
      "symbols": ""
    },
    {
      "name": "كثير بْن مرة الحضرمي",
      "symbols": "(د)"
    },
    {
      "name": "كعب الأحبار",
      "symbols": "(فق)"
    },
    {
      "name": "مالك بْن يخامر السكسكي",
      "symbols": ""
    },
    {
      "name": "معاوية بْن أَبي سُفْيَان",
      "symbols": ""
    },
    {
      "name": "المقداد بْن الأسود",
      "symbols": ""
    },
    {
      "name": "المقدام بْن مَعْدِي كَرِب",
      "symbols": "(د)"
    },
    {
      "name": "يزيد بْن خمير اليزني",
      "symbols": ""
    },
    {
      "name": "يزيد بْن ميسرة بْن حلبس",
      "symbols": ""
    },
    {
      "name": "أَبِي إدريس الخولاني",
      "symbols": ""
    },
    {
      "name": "أَبي الدَّرْدَاء",
      "symbols": "(ق)"
    },
    {
      "name": "أَبِي ذر الغفاري",
      "symbols": ""
    },
    {
      "name": "أَبِي راشد الحبراني",
      "symbols": "(د)"
    },
    {
      "name": "أَبِي رهم السماعي",
      "symbols": ""
    },
    {
      "name": "أَبِي زهير النميري",
      "symbols": ""
    },
    {
      "name": "أَبِي طيبة الكلاعي",
      "symbols": "(د)"
    },
    {
      "name": "أَبِي عذبة الحضرمي الحمصي",
      "symbols": ""
    },
    {
      "name": "أَبِي مَالِك الأشعري",
      "symbols": "(د)"
    },
    {
      "name": "أَبِي مسلم الجليلي",
      "symbols": ""
    }
  ],
  "students": [
    {
      "name": "ثور بْن يزيد الرحبي",
      "symbols": ""
    },
    {
      "name": "صفوان بْن عَمْرو",
      "symbols": "(د س ق)"
    },
    {
      "name": "ضمرة بْن ربيعة",
      "symbols": "(د فق)"
    },
    {
      "name": "ضمضم بْن زرعة",
      "symbols": "(د فق)"
    },
    {
      "name": "أَبُو دوس عُثْمَان بْن عُبَيد اليحصبي",
      "symbols": ""
    },
    {
      "name": "معاوية بْن صالح الحضرمي الحمصي",
      "symbols": ""
    }
  ]
}