{
  "knownName": "عمر بن مالك الشرعبي",
  "teachers": [
    {
      "name": "خَالِد بْن أَبي عِمْران",
      "symbols": ""
    },
    {
      "name": "صفوان بْن سليم",
      "symbols": ""
    },
    {
      "name": "عُبَيد الله بْن أَبي جعفر",
      "symbols": "(د س)"
    },
    {
      "name": "يزيد بْن عَبد اللَّهِ بْن الهاد",
      "symbols": "(م د س)"
    }
  ],
  "students": [
    {
      "name": "حيوة بْن شريح",
      "symbols": ""
    },
    {
      "name": "ضمام بن إسماعيل",
      "symbols": ""
    },
    {
      "name": "عبد الله بْن لَهِيعَة",
      "symbols": ""
    },
    {
      "name": "عبد الله بْن وهب",
      "symbols": "(م د س)"
    },
    {
      "name": "عبد الرحمن بْن شريح الإسكندراني",
      "symbols": ""
    },
    {
      "name": "مغيرة بْن الحسن بْن راشد مولى بني هاشم",
      "symbols": ""
    }
  ]
}