{
  "knownName": "عمرو بن منصور الهمداني",
  "teachers": [
    {
      "name": "الحجاج بْن فرافصة",
      "symbols": ""
    },
    {
      "name": "عامر الشعبي",
      "symbols": "(د)"
    }
  ],
  "students": [
    {
      "name": "إبراهيم بْن عُيَيْنَة",
      "symbols": "(د)"
    },
    {
      "name": "أخوه عِمْران بْن عُيَيْنَة",
      "symbols": ""
    },
    {
      "name": "عيسى بْن يونس بْن أَبي إسحاق",
      "symbols": ""
    },
    {
      "name": "مُحَمَّد بْن مروان الكوفي",
      "symbols": ""
    },
    {
      "name": "وكيع بْن الجراح",
      "symbols": ""
    },
    {
      "name": "يونس بْن أَبي إسحاق",
      "symbols": ""
    }
  ]
}