{
  "knownName": "عون بن عبد الله",
  "teachers": [
    {
      "name": "أَبِي فاختة سَعِيد بْن علاقة",
      "symbols": "(ق)"
    },
    {
      "name": "سَعِيد بْن المُسَيَّب",
      "symbols": ""
    },
    {
      "name": "عامر الشعبي",
      "symbols": "(م)"
    },
    {
      "name": "عَبْد اللَّهِ بْن عَبَّاسٍ",
      "symbols": ""
    },
    {
      "name": "أبيه عَبد الله بْن عتبة بْن مسعود",
      "symbols": "(م د س ق)"
    },
    {
      "name": "عبد اللَّهِ بْن عُمَر بْن الخطاب",
      "symbols": "(م ت س)"
    },
    {
      "name": "عبد اللَّه بن عَمْرو بن العاص",
      "symbols": "(سي)"
    },
    {
      "name": "عم أبيه عَبد الله بْن مسعود",
      "symbols": "(د ت ق)"
    },
    {
      "name": "أخيه عُبَيد اللَّه بْن عَبد اللَّه بْن عتبة",
      "symbols": "(مد)"
    },
    {
      "name": "يوسف بن عَبد اللَّهِ بن سلام",
      "symbols": "(سي)"
    },
    {
      "name": "أبي بردة بْن أَبي موسى الأشعري",
      "symbols": "(م)"
    },
    {
      "name": "أبي هُرَيْرة",
      "symbols": ""
    },
    {
      "name": "أسماء بنت أَبِي بكر",
      "symbols": ""
    },
    {
      "name": "أختها عائشة بنت أَبِي بكر زوج النَّبِيُّ صلى الله عليه وسلم",
      "symbols": ""
    },
    {
      "name": "أم الدرداء",
      "symbols": "(س)"
    }
  ],
  "students": [
    {
      "name": "إسحاق بْن يزيد الهذلي",
      "symbols": "(د ت ق)"
    },
    {
      "name": "إسماعيل بْن أَبي خالد",
      "symbols": ""
    },
    {
      "name": "جعفر بْن ربيعة",
      "symbols": "(سي)"
    },
    {
      "name": "حماد بْن حميد المدني",
      "symbols": "(ق)"
    },
    {
      "name": "أخوه حمزة بْن عَبد الله بْن عتبة بْن مسعود",
      "symbols": ""
    },
    {
      "name": "حنظلة بْن أَبي سفيان الجمحي",
      "symbols": ""
    },
    {
      "name": "زيد العمي",
      "symbols": ""
    },
    {
      "name": "سَعِيد بْن أَبي سَعِيد المقبري",
      "symbols": ""
    },
    {
      "name": "سَعِيد بْن أَبي هلال المِصْرِي",
      "symbols": "(م س)"
    },
    {
      "name": "أَبُو حازم سلمة بْن دينار",
      "symbols": ""
    },
    {
      "name": "شَرِيك بْن عَبد اللَّه بْن أَبي نمر",
      "symbols": ""
    },
    {
      "name": "شَيْبَة بْن المساور",
      "symbols": ""
    },
    {
      "name": "صالح بْن صالح بْن حي",
      "symbols": ""
    },
    {
      "name": "عبد اللَّه بْن الْوَلِيد المزني",
      "symbols": ""
    },
    {
      "name": "عَبْد الرَّحْمَنِ بْن عَبد اللَّهِ المسعودي",
      "symbols": "(د ق)"
    },
    {
      "name": "عبد الرحمن بْن مُحَمَّد بْن عَبد الله بن عبد القاري والد يعقوب بْن عَبْد الرَّحْمَنِ",
      "symbols": ""
    },
    {
      "name": "عبد العزيز بْن عُبَيد اللَّه بْن حمزة بْن صهيب",
      "symbols": ""
    },
    {
      "name": "أَبُو العميس عتبة بْن عَبد اللَّهِ المسعودي",
      "symbols": "(مد)"
    },
    {
      "name": "عَمْرو بْن مرة",
      "symbols": "(س)"
    },
    {
      "name": "عيسى بْن عُمَر النحوي",
      "symbols": ""
    },
    {
      "name": "قتادة",
      "symbols": "(م)"
    },
    {
      "name": "قرة بْن خالد",
      "symbols": ""
    },
    {
      "name": "مالك بْن مغول",
      "symbols": ""
    },
    {
      "name": "مجالد بْن سَعِيد",
      "symbols": ""
    },
    {
      "name": "مُحَمَّد بْن سوقة",
      "symbols": ""
    },
    {
      "name": "مُحَمَّد بْن عجلان",
      "symbols": "(ت س ق)"
    },
    {
      "name": "محمد بْن مسلم بْن شهاب الزُّهْرِيّ",
      "symbols": ""
    },
    {
      "name": "مسعر بْن كدام",
      "symbols": ""
    },
    {
      "name": "مطرف بْن معقل الشقري",
      "symbols": ""
    },
    {
      "name": "معن بْن عَبْد الرحمن المسعودي",
      "symbols": ""
    },
    {
      "name": "موسى بْن أَبي عيسى الطحان",
      "symbols": "(ق)"
    },
    {
      "name": "موسى الجهني",
      "symbols": ""
    },
    {
      "name": "أَبُو سهيل نافع بْن مالك بْن أَبي عامر الأصبحي",
      "symbols": ""
    },
    {
      "name": "أبو حنيفة النعمان ابن ثابت",
      "symbols": ""
    },
    {
      "name": "نوفل بْن الفرات",
      "symbols": ""
    },
    {
      "name": "يحيى بْن جابر الطائي",
      "symbols": ""
    },
    {
      "name": "يحيى بْن عَبد اللَّهِ بن بحير بن ريسان",
      "symbols": ""
    },
    {
      "name": "يحيى بْن عَبْد الرحمن الثقفي",
      "symbols": "(سي)"
    },
    {
      "name": "يعقوب بْن عَبد اللَّه بْن الأشج",
      "symbols": ""
    },
    {
      "name": "أَبُو إسحاق الشيباني",
      "symbols": ""
    },
    {
      "name": "أَبُو الزبير المكي",
      "symbols": "(م ت س)"
    },
    {
      "name": "أَبُو علقمة مولى بني هاشم",
      "symbols": ""
    }
  ]
}