{
  "knownName": "المسور بن مخرمة",
  "teachers": [
    {
      "name": "رَسُول اللَّهِ صلى الله عليه وسَلَّمَ",
      "symbols": "(ع)"
    },
    {
      "name": "عَبد الله بْن عباس",
      "symbols": "(ع)"
    },
    {
      "name": "عَبْد الرحمن بْن عوف",
      "symbols": "(بخ)"
    },
    {
      "name": "عثمان بْن عفان",
      "symbols": ""
    },
    {
      "name": "علي بْن أَبي طالب",
      "symbols": ""
    },
    {
      "name": "عُمَر بن الخطاب",
      "symbols": "(خ م ت س)"
    },
    {
      "name": "عَمْرو بْن عوف",
      "symbols": "(خ م ت س ق)"
    },
    {
      "name": "محمد بْن مسلمة الأَنْصارِيّ",
      "symbols": "(م د ق)"
    },
    {
      "name": "أبيه مخرمة بن نوفل",
      "symbols": ""
    },
    {
      "name": "معاوية بن أَبي سفيان",
      "symbols": ""
    },
    {
      "name": "المغيرة بْن شعبة",
      "symbols": "(م د ق)"
    },
    {
      "name": "أَبِي بَكْر الصديق",
      "symbols": ""
    },
    {
      "name": "أبي هُرَيْرة",
      "symbols": ""
    }
  ],
  "students": [
    {
      "name": "أَبُو أمامة أسعد بْن سهل بْن حنيف",
      "symbols": "(م د)"
    },
    {
      "name": "جهم بْن أَبي الجهم الجمحي",
      "symbols": ""
    },
    {
      "name": "سَعِيد بْن المُسَيَّب",
      "symbols": ""
    },
    {
      "name": "سُلَيْمان بْن يسار",
      "symbols": ""
    },
    {
      "name": "عبد اللَّهِ بْن حنين",
      "symbols": "(خ م كن)"
    },
    {
      "name": "عَبْد الله بْن عُبَيد اللَّه بْن أَبي مليكة",
      "symbols": "(ع)"
    },
    {
      "name": "عُبَيد اللَّه بْن أَبي رافع",
      "symbols": ""
    },
    {
      "name": "عُبَيد الله بْن عَبد الله بْن عتبة بْن مسعود",
      "symbols": ""
    },
    {
      "name": "عروة بْن الزبير بْن العوام",
      "symbols": "(ع)"
    },
    {
      "name": "علي بْن الْحُسَيْن بْن عَلِيٍّ بْن أَبي طالب",
      "symbols": "(خ م د س ق)"
    },
    {
      "name": "عَمْرو بْن دينار",
      "symbols": ""
    },
    {
      "name": "عوف بْن الطفيل",
      "symbols": ""
    },
    {
      "name": "مروان بْن الحكم",
      "symbols": ""
    },
    {
      "name": "ابنته أم بكر بنت المسور بْن مخرمة",
      "symbols": "(بخ)"
    }
  ]
}