{
  "knownName": "موسى بن عبيدة الربذي",
  "teachers": [
    {
      "name": "أبان بْن صالح",
      "symbols": ""
    },
    {
      "name": "إبراهيم بْن عَبد اللَّهِ بْنِ حنين",
      "symbols": ""
    },
    {
      "name": "إياس بن سلمة بن الأكوع",
      "symbols": "(تم ق)"
    },
    {
      "name": "أيوب بن خالد",
      "symbols": "(ت)"
    },
    {
      "name": "جهمان الأَسلميّ",
      "symbols": "(ق)"
    },
    {
      "name": "داود بن مدرك",
      "symbols": "(ق)"
    },
    {
      "name": "سَعِيد بْن أَبي سَعِيد",
      "symbols": "(س ق)"
    },
    {
      "name": "أبي حازم سلمة بن دينار",
      "symbols": ""
    },
    {
      "name": "صالح بن سويد",
      "symbols": ""
    },
    {
      "name": "صدقة بن يَسَارٍ",
      "symbols": ""
    },
    {
      "name": "طلحة بن عُبَيد اللَّهِ بْن كريز",
      "symbols": ""
    },
    {
      "name": "عَبد اللَّه بْن دينار",
      "symbols": "(ت ق)"
    },
    {
      "name": "عَبد الله بن رافع",
      "symbols": "(ت)"
    },
    {
      "name": "أخيه عَبد اللَّهِ بن عُبَيدة الربذي",
      "symbols": ""
    },
    {
      "name": "عبد الرحمن بْن أَبي سَعِيد الخُدْرِيّ",
      "symbols": ""
    },
    {
      "name": "علقمة ابن مرثد",
      "symbols": "(ق)"
    },
    {
      "name": "عُمَر بن الحكم بن ثوبان",
      "symbols": ""
    },
    {
      "name": "القاسم بن مهران",
      "symbols": "(ق)"
    },
    {
      "name": "محمد بْن إِبْرَاهِيم بْن الحارث التَّيْمِيّ",
      "symbols": ""
    },
    {
      "name": "محمد بن ثابت",
      "symbols": "(ت ق)"
    },
    {
      "name": "محمد بْن عَبْدِ الرَّحْمَنِ بن أَبي عياش الزرقي",
      "symbols": ""
    },
    {
      "name": "أخيه مُحَمَّد بن عُبَيدة الربذي",
      "symbols": ""
    },
    {
      "name": "محمد بْن عَمْرو بْن عطاء",
      "symbols": "(ق)"
    },
    {
      "name": "محمد ابن كعب القرظي",
      "symbols": "(ت)"
    },
    {
      "name": "محمد بْن المنكدر",
      "symbols": ""
    },
    {
      "name": "مصعب بن محمد ابن شرحبيل",
      "symbols": "(ق)"
    },
    {
      "name": "موسى بن مُحَمَّد بن إِبْرَاهِيمَ التَّيْمِيّ",
      "symbols": ""
    },
    {
      "name": "نافع مولى ابْن عُمَر",
      "symbols": ""
    },
    {
      "name": "هود بْن عطاء",
      "symbols": ""
    },
    {
      "name": "يحيى بن حرب",
      "symbols": "(ق)"
    },
    {
      "name": "يزيد ابن أبان الرقاشي",
      "symbols": "(ت)"
    },
    {
      "name": "يعقوب بن زيد التَّيْمِيّ",
      "symbols": ""
    },
    {
      "name": "يوسف بن طهمان",
      "symbols": ""
    },
    {
      "name": "مولى ابن سباع",
      "symbols": "(ت)"
    }
  ],
  "students": [
    {
      "name": "ابن أخيه بكار بن عَبد اللَّهِ بن عُبَيدة الربذي",
      "symbols": ""
    },
    {
      "name": "بهلول بْن مورق",
      "symbols": "(ق)"
    },
    {
      "name": "جعفر بن عَوْنٍ",
      "symbols": ""
    },
    {
      "name": "حماد بن عِيسَى الجهني",
      "symbols": "(ق)"
    },
    {
      "name": "روح بن عبادة",
      "symbols": "(ت)"
    },
    {
      "name": "زيد بْن الحباب",
      "symbols": "(ت ق)"
    },
    {
      "name": "سَعِيدابن سلام بْن أَبي الهيفاء",
      "symbols": ""
    },
    {
      "name": "سفيان الثوري",
      "symbols": "(ت)"
    },
    {
      "name": "سُلَيْمان بْن بلال",
      "symbols": ""
    },
    {
      "name": "شعبة بْن الحجاج",
      "symbols": ""
    },
    {
      "name": "عَبد الله بْن داود الخريبي",
      "symbols": ""
    },
    {
      "name": "عبد الله بن المبارك",
      "symbols": "(تم ق)"
    },
    {
      "name": "عَبد اللَّه بْن نمير",
      "symbols": "(ت ق)"
    },
    {
      "name": "عبد الرحمن بْن مُحَمَّد المحاربي",
      "symbols": ""
    },
    {
      "name": "عَبد الرحيم بْن سُلَيْمان",
      "symbols": ""
    },
    {
      "name": "عبد العزيز بن مُحَمَّد الدَّراوَرْدِيّ",
      "symbols": "(ق)"
    },
    {
      "name": "عُبَيد اللَّه بْن مُوسَى",
      "symbols": "(ت ق)"
    },
    {
      "name": "علي بن صالح",
      "symbols": ""
    },
    {
      "name": "علي بن مجاهد",
      "symbols": ""
    },
    {
      "name": "عيسى بن يونس",
      "symbols": "(ت)"
    },
    {
      "name": "قران ابن تمام الأسدي",
      "symbols": "(ت)"
    },
    {
      "name": "محمد بن إِسماعيل بن طريح الثقفي",
      "symbols": ""
    },
    {
      "name": "أَبُو معاوية مُحَمَّد بْن خازم الضرير",
      "symbols": ""
    },
    {
      "name": "أبو همام مُحَمَّد بْن الزبرقان الأهوازي",
      "symbols": "(ق)"
    },
    {
      "name": "محمد بن القاسم الأسدي",
      "symbols": ""
    },
    {
      "name": "مروان بن معاوية الفزاري",
      "symbols": ""
    },
    {
      "name": "معافى بن عِمْران الموصلي",
      "symbols": ""
    },
    {
      "name": "مكي بْن إِبْرَاهِيم البلخي",
      "symbols": ""
    },
    {
      "name": "موسى بْن أعين الجزري",
      "symbols": ""
    },
    {
      "name": "النعمان بن عبد السلام الأصبهاني",
      "symbols": ""
    },
    {
      "name": "وكيع بْن الجراح",
      "symbols": "(ت ق)"
    },
    {
      "name": "أَبُو تميلة يَحْيَى بن واضح",
      "symbols": ""
    }
  ]
}