{
  "knownName": "موسى بن عمير",
  "teachers": [
    {
      "name": "جعفر بن مُحَمَّد الصادق",
      "symbols": ""
    },
    {
      "name": "الحكم بن عتيبة",
      "symbols": ""
    },
    {
      "name": "عامر الشعبي",
      "symbols": ""
    },
    {
      "name": "عطية العوفي",
      "symbols": ""
    },
    {
      "name": "محمد بن مسلم بن شهاب الزُّهْرِيّ",
      "symbols": ""
    },
    {
      "name": "مكحول الشامي",
      "symbols": ""
    },
    {
      "name": "أبي جعفر الباقر",
      "symbols": ""
    },
    {
      "name": "أبي الزناد",
      "symbols": ""
    },
    {
      "name": "أبي صالح مولى أم هانئ",
      "symbols": ""
    }
  ],
  "students": [
    {
      "name": "إسحاق بن كعب البغدادي مولى بني هاشم",
      "symbols": ""
    },
    {
      "name": "جبارة بن مغلس",
      "symbols": ""
    },
    {
      "name": "جعفر بن حميد القرشي",
      "symbols": ""
    },
    {
      "name": "الحسن بن زيادمؤذن بني محارب",
      "symbols": ""
    },
    {
      "name": "سويد بن سَعِيد الحدثاني",
      "symbols": ""
    },
    {
      "name": "عباد بن يَعْقُوبَ الرواجني",
      "symbols": ""
    },
    {
      "name": "علي بن أَبي طالب البزاز",
      "symbols": ""
    },
    {
      "name": "محمد بن عُبَيد المحاربي",
      "symbols": ""
    },
    {
      "name": "مُحَمَّد بن عيسى ابن الطباع",
      "symbols": ""
    },
    {
      "name": "أبو صهيب النضر بْن سَعِيد بْن النضر بْن شبرمة الحارثي الكوفي",
      "symbols": ""
    },
    {
      "name": "الهيثم بن يمان",
      "symbols": ""
    }
  ]
}