{
  "knownName": "أبو عقال هلال بن زيد",
  "teachers": [
    {
      "name": "أنس بْن مالك",
      "symbols": "(ق)"
    }
  ],
  "students": [
    {
      "name": "إِبْرَاهِيم بْن سويد بن حيان",
      "symbols": ""
    },
    {
      "name": "داود بن عجلان",
      "symbols": "(ق)"
    },
    {
      "name": "أَبُو صدقة صخر بن صدقة اليمامي",
      "symbols": ""
    },
    {
      "name": "عباد بن كثير الرملي",
      "symbols": ""
    },
    {
      "name": "عَبْد اللَّهِ بْن واقد بن زيد العُمَري",
      "symbols": ""
    },
    {
      "name": "عقبة بن علقمة البيروتي",
      "symbols": ""
    },
    {
      "name": "عُمَر ابن محمد بن زيد العُمَري",
      "symbols": ""
    },
    {
      "name": "أخوه واقد بن محمد بن زيد العُمَري",
      "symbols": ""
    }
  ]
}