{
  "knownName": "وهب بن بقية",
  "teachers": [
    {
      "name": "أغلب بْن تميم",
      "symbols": ""
    },
    {
      "name": "بشر بْن المفضل",
      "symbols": "(مد)"
    },
    {
      "name": "جعفر ابن سُلَيْمان الضبعي",
      "symbols": ""
    },
    {
      "name": "حاتم بْن الأَحنف الْوَاسِطِيّ",
      "symbols": ""
    },
    {
      "name": "الحكم بْن ظهير",
      "symbols": ""
    },
    {
      "name": "حماد بْن زيد",
      "symbols": ""
    },
    {
      "name": "خالد بْن عَبد اللَّهِ الواسطي",
      "symbols": "(م د س)"
    },
    {
      "name": "سحت بْن إِبْرَاهِيم الْوَاسِطِيّ",
      "symbols": ""
    },
    {
      "name": "سليم بن أخضر",
      "symbols": ""
    },
    {
      "name": "عبد الله بْن سُفْيَان المدني ثُمَّ الْوَاسِطِيّ",
      "symbols": ""
    },
    {
      "name": "عبد الأعلى بْن عبد الاعلى",
      "symbols": ""
    },
    {
      "name": "عبد الوهاب الثقفي",
      "symbols": ""
    },
    {
      "name": "عُمَر بن يُونُس اليمامي",
      "symbols": "(د)"
    },
    {
      "name": "مُحَمَّد بْن عَبد المَلِك الواسطي الكبير",
      "symbols": ""
    },
    {
      "name": "مُحَمَّد بْن هَارُون بْن عُبَيد الْوَاسِطِيّ",
      "symbols": ""
    },
    {
      "name": "مرحوم بْن عبد العزيز العطار",
      "symbols": ""
    },
    {
      "name": "أبي مطرف المغيرة بْن مطرف، الْوَاسِطِيّ",
      "symbols": ""
    },
    {
      "name": "نوح بْن قيس الحداني",
      "symbols": "(د)"
    },
    {
      "name": "هشيم بْن بشير",
      "symbols": "(د)"
    },
    {
      "name": "يحيى بْن عَبد المَلِك بْن أَبي غنية",
      "symbols": ""
    },
    {
      "name": "يزيد بْن زريع",
      "symbols": "(مد)"
    },
    {
      "name": "أبي خَالِد الأحمر",
      "symbols": "(د)"
    },
    {
      "name": "أبي داود الطيالسي",
      "symbols": ""
    },
    {
      "name": "أبي معاوية الضرير",
      "symbols": "(د)"
    }
  ],
  "students": [
    {
      "name": "مسلم",
      "symbols": ""
    },
    {
      "name": "أَبُو داود",
      "symbols": ""
    },
    {
      "name": "إبراهيم بْن أيوب الْوَاسِطِيّ العدل",
      "symbols": ""
    },
    {
      "name": "أَبُو الْوَلِيد أَحْمَد بْن بِشْر الطيالسي",
      "symbols": ""
    },
    {
      "name": "أَحْمَد بْن الْحَسَن الْوَاسِطِيّ",
      "symbols": ""
    },
    {
      "name": "أَبُو بَكْر أَحْمَد بْن علي بْن سَعِيد القاضي المروزي",
      "symbols": ""
    },
    {
      "name": "أَبُو يَعْلَى أَحْمَد بْن علي بْن المثنى الموصلي",
      "symbols": ""
    },
    {
      "name": "أَبُو بَكْر أَحْمَد بْن عَمْرو بْن أَبي عاصم",
      "symbols": ""
    },
    {
      "name": "أحمد بْن مُحَمَّد بْن أَنَس البغدادي",
      "symbols": ""
    },
    {
      "name": "أَحْمَد بْن يَحْيَى بْن جابر البلاذري",
      "symbols": ""
    },
    {
      "name": "إدريس بْن عَبْد الكريم الحداد المقرئ",
      "symbols": ""
    },
    {
      "name": "أسلم بْن سهل الواسطي بحشل",
      "symbols": ""
    },
    {
      "name": "إسماعيل بْن عَبد اللَّهِ الأصبهاني سمويه",
      "symbols": ""
    },
    {
      "name": "بقي بْن مخلد الأندلسي",
      "symbols": ""
    },
    {
      "name": "جعفر بْن أَحْمَدَ بْن مُحَمَّد بن الصباح الجرجرائي",
      "symbols": ""
    },
    {
      "name": "جعفر بن مُحَمَّد الفريابي",
      "symbols": ""
    },
    {
      "name": "الحسين بْن إسحاق التستري",
      "symbols": ""
    },
    {
      "name": "حنبل بن إسحاق بن حنبل",
      "symbols": ""
    },
    {
      "name": "زكريا بْن يَحْيَى السجزي",
      "symbols": "(س)"
    },
    {
      "name": "عَبد الله بن أَحْمَد بْن حنبل",
      "symbols": ""
    },
    {
      "name": "أَبُو الْقَاسِم عَبد اللَّهِ بْن مُحَمَّد بْن عَبْد الْعَزِيزِ البغوي",
      "symbols": ""
    },
    {
      "name": "عبد الله بْن مُحَمَّد بْن ناجية",
      "symbols": ""
    },
    {
      "name": "عبد الله بْن موسى بْن أَبي عثمان البزاز",
      "symbols": ""
    },
    {
      "name": "عبدان بْن أَحْمَد الأهوازي",
      "symbols": ""
    },
    {
      "name": "عثمان بْن خرزاذ، الأنطاكي",
      "symbols": ""
    },
    {
      "name": "علي بْن إِسْحَاق بْن زاطيا",
      "symbols": ""
    },
    {
      "name": "مُحَمَّد بْن إسحاق الثقفي السراج",
      "symbols": ""
    },
    {
      "name": "محمد بْن بشر بْن مطر أخو خطاب",
      "symbols": ""
    },
    {
      "name": "مُحَمَّد بْن سُلَيْمان المقري",
      "symbols": ""
    },
    {
      "name": "محمد بن عبدوس كَامِل السراج",
      "symbols": ""
    },
    {
      "name": "محمود بْن مُحَمَّد الْوَاسِطِيّ",
      "symbols": ""
    },
    {
      "name": "أَبُو زُرْعَة الرازي",
      "symbols": ""
    }
  ]
}