{
  "knownName": "يحيى بن جابر",
  "teachers": [
    {
      "name": "جُبَيْر بْن نفير",
      "symbols": "(د)"
    },
    {
      "name": "حكيم بْن معاوية",
      "symbols": "(ق)"
    },
    {
      "name": "معاوية بْن حكيم النميري",
      "symbols": "(ت)"
    },
    {
      "name": "صالح بْن يَحْيَى بْن المقدام بْن مَعْدِي كَرِب",
      "symbols": "(د)"
    },
    {
      "name": "ضمرة بْن ثعلبة السُّلَمِيّ",
      "symbols": ""
    },
    {
      "name": "عبد الله بْن حوالة",
      "symbols": ""
    },
    {
      "name": "عَبْد الرَّحْمَنِ بْن جبير بْن نفير",
      "symbols": "(بخ م ٤)"
    },
    {
      "name": "عبد الرحمن بْن عائذ الأزدي",
      "symbols": ""
    },
    {
      "name": "عبد الرحمن بْن عَمْرو السُّلَمِيّ",
      "symbols": ""
    },
    {
      "name": "عوف بْن مَالِك الأشجعي",
      "symbols": "(د)"
    },
    {
      "name": "المقدام بْن مَعْدِي كَرِب",
      "symbols": "(ت س)"
    },
    {
      "name": "النواس بْن سمعان",
      "symbols": ""
    },
    {
      "name": "يزيد بْن شريح الحضرمي",
      "symbols": "(مد)"
    },
    {
      "name": "يزيد بْن ميسرة بْن حلبس",
      "symbols": ""
    },
    {
      "name": "أبي ثعلبة النهدي صاحب النَّبِيّ صلى الله عليه وسلم",
      "symbols": ""
    },
    {
      "name": "أبي سورة",
      "symbols": "(د)"
    },
    {
      "name": "أبي مرحوم الحمصي العطار",
      "symbols": ""
    }
  ],
  "students": [
    {
      "name": "حَبِيب بْن صَالِح بْن حَبِيب قاضي حمص",
      "symbols": "(ت)"
    },
    {
      "name": "أَبُو سَلَمَة سُلَيْمان بْن سليم",
      "symbols": "(٤)"
    },
    {
      "name": "صفوان بْن عَمْرو",
      "symbols": ""
    },
    {
      "name": "عبد الرحمن ابن يَزِيد بْن جَابِر",
      "symbols": "(م ٤)"
    },
    {
      "name": "مُحَمَّد بْن الْوَلِيد الزبيدي",
      "symbols": "(بخ د)"
    },
    {
      "name": "معاوية بْن صَالِحٍ الحضرمي",
      "symbols": "(س)"
    },
    {
      "name": "أَبُو راشد التنوخي",
      "symbols": ""
    }
  ]
}