{
  "knownName": "خاقان",
  "teachers": [
    {
      "name": "حَفْص بْن غِيَاث",
      "symbols": ""
    },
    {
      "name": "عبد الله بْن المبارك",
      "symbols": "(خ)"
    },
    {
      "name": "أبي عصمة نوح بْن أَبي مَرْيَم",
      "symbols": ""
    },
    {
      "name": "وكيع بْن الجراح",
      "symbols": ""
    },
    {
      "name": "الوليد بْن مسلم",
      "symbols": ""
    }
  ],
  "students": [
    {
      "name": "البخاري",
      "symbols": ""
    },
    {
      "name": "حاشد بْن إِسْمَاعِيل الْبُخَارِيّ",
      "symbols": ""
    },
    {
      "name": "حمزة ابن العباس الْمَرْوَزِيّ",
      "symbols": ""
    },
    {
      "name": "سفيان بْن عبد الحكيم الْبُخَارِيّ",
      "symbols": ""
    },
    {
      "name": "عبد الله بْن علي الكرماني",
      "symbols": ""
    },
    {
      "name": "أَبُو الليث عُبَيد اللَّهِ بْن سريج الْبُخَارِيّ الْحَافِظ",
      "symbols": ""
    },
    {
      "name": "عُبَيد الله بن عَمْرو بن حَفْص بْن إِبْرَاهِيم البزدوي، النسفي",
      "symbols": ""
    },
    {
      "name": "محمد بْن إسحاق الثقفي السراج",
      "symbols": ""
    },
    {
      "name": "محمد بْن علي بْن الْحَسَن بْن شقيق",
      "symbols": ""
    },
    {
      "name": "أَبُو عَبْد الرَّحْمَنِ الأزدي",
      "symbols": ""
    }
  ]
}