{
  "knownName": "أَبُو بكر الهذلي البَصْرِيّ",
  "teachers": [
    {
      "name": "الحسن البَصْرِيّ",
      "symbols": ""
    },
    {
      "name": "خالد الربعي",
      "symbols": ""
    },
    {
      "name": "سلمة بْن جنادة الهذلي",
      "symbols": ""
    },
    {
      "name": "شهر بْن حوشب",
      "symbols": "(ق)"
    },
    {
      "name": "عامر الشعبي",
      "symbols": ""
    },
    {
      "name": "عكرمة مولى ابْن عباس",
      "symbols": ""
    },
    {
      "name": "عون بْن عَبد الله بْن عتبة بْن مسعود",
      "symbols": ""
    },
    {
      "name": "قتادة بْن دعامة",
      "symbols": "(ق)"
    },
    {
      "name": "قزعة بْن يَحْيَى",
      "symbols": ""
    },
    {
      "name": "مُحَمَّد بن سيرين",
      "symbols": "(ق)"
    },
    {
      "name": "محمد ابن المنكدر",
      "symbols": ""
    },
    {
      "name": "أبي تميمة الهجيمي",
      "symbols": ""
    },
    {
      "name": "أبي الزبير المكي",
      "symbols": ""
    },
    {
      "name": "أبي المليح الهذلي",
      "symbols": ""
    },
    {
      "name": "معاذة العدوية",
      "symbols": ""
    }
  ],
  "students": [
    {
      "name": "أسباط بن محمد القرشي",
      "symbols": ""
    },
    {
      "name": "إسماعيل بن عياش",
      "symbols": "(ق)"
    },
    {
      "name": "أيوب بْن سويد الرملي",
      "symbols": "(ق)"
    },
    {
      "name": "الحسن بْن عَمْرو بْن سيف العبدي البَصْرِيّ",
      "symbols": ""
    },
    {
      "name": "الحسن بْن قتيبة المدائني",
      "symbols": ""
    },
    {
      "name": "حفص بْن عَبد اللَّه السلمي قاضي نيسابور",
      "symbols": ""
    },
    {
      "name": "سفيان بْن عُيَيْنَة",
      "symbols": ""
    },
    {
      "name": "سُلَيْمان التَّيْمِيّ",
      "symbols": ""
    },
    {
      "name": "شبابة بْن سوار",
      "symbols": ""
    },
    {
      "name": "عامر بْن صالح بْن رستم",
      "symbols": ""
    },
    {
      "name": "عبد الملك بْن جُرَيْج",
      "symbols": ""
    },
    {
      "name": "أبو نعيم الفضل بْن دكين",
      "symbols": ""
    },
    {
      "name": "القاسم بْن الحكم العرني",
      "symbols": ""
    },
    {
      "name": "مُحَمَّد بْن مناذر الشاعر",
      "symbols": ""
    },
    {
      "name": "مسلم بْن إِبْرَاهِيم",
      "symbols": ""
    },
    {
      "name": "معلى بْن الفضل",
      "symbols": ""
    },
    {
      "name": "وكيع بْن الجراح",
      "symbols": "(ق)"
    }
  ]
}