{
  "knownName": "أبو العباس القلوري",
  "teachers": [
    {
      "name": "سَعِيد بْن عامر الضبعي",
      "symbols": ""
    },
    {
      "name": "عبد الرحمن بْن حماد الشعيثي",
      "symbols": ""
    },
    {
      "name": "عثمان بْن زفر",
      "symbols": ""
    },
    {
      "name": "عثمان بْن عُمَر بْن فارس",
      "symbols": ""
    },
    {
      "name": "علي بْن عثمان اللاحقي",
      "symbols": ""
    },
    {
      "name": "قرة بْن حبيب القنوي",
      "symbols": ""
    },
    {
      "name": "أبي غسان يَحْيَى بْن كثير العنبري",
      "symbols": ""
    },
    {
      "name": "يعقوب بْن إسحاق الحضرمي",
      "symbols": "(د)"
    }
  ],
  "students": [
    {
      "name": "أَبُو داود",
      "symbols": ""
    },
    {
      "name": "أبو بكر أَحْمَد بْن عَمْرو بْن عبد الخالق البزار",
      "symbols": ""
    },
    {
      "name": "أبو بكر أَحْمَد بْن مُحَمَّد بْن صدقة",
      "symbols": ""
    },
    {
      "name": "أبو عَرُوبَة الْحُسَيْنُ بْنُ أَبي مَعْشَرٍ الْحِرَّانِيُّ",
      "symbols": ""
    },
    {
      "name": "سَعِيد بْن عَبد اللَّهِ بْن سَعِيد المهراني",
      "symbols": ""
    },
    {
      "name": "محمد بْن جرير، الطبري",
      "symbols": ""
    },
    {
      "name": "مُحَمَّد بن العباس بن أيوب بْن الأخرم الأصبهاني",
      "symbols": ""
    },
    {
      "name": "محمد بْن مُحَمَّد بْن سُلَيْمان الباغندي",
      "symbols": ""
    },
    {
      "name": "يحيى بْن مُحَمَّد بْن صاعد",
      "symbols": ""
    },
    {
      "name": "أبو العباس الهروي",
      "symbols": ""
    }
  ]
}