{
  "knownName": "بهز بن حكيم",
  "teachers": [
    {
      "name": "أبيه عَنْ جده",
      "symbols": "(خت ٤)"
    },
    {
      "name": "زرارة بْن أوفى",
      "symbols": "(د ت)"
    },
    {
      "name": "هشام بْن عروة",
      "symbols": ""
    }
  ],
  "students": [
    {
      "name": "إسماعيل بن علية",
      "symbols": "(د س ق)"
    },
    {
      "name": "أصبغ",
      "symbols": ""
    },
    {
      "name": "بشر بْن المفضل",
      "symbols": ""
    },
    {
      "name": "جرير بْن حازم",
      "symbols": ""
    },
    {
      "name": "أَبُو أسامة حماد بْن أسامة",
      "symbols": "(د ق)"
    },
    {
      "name": "حماد بْن زيد",
      "symbols": ""
    },
    {
      "name": "حماد بْن سلمة",
      "symbols": "(د)"
    },
    {
      "name": "خالد بْن عَبْد اللَّهِ الواسطي",
      "symbols": ""
    },
    {
      "name": "روح بْن عبادة",
      "symbols": ""
    },
    {
      "name": "زكريا بْن أَبي عُبَيدة الناجي",
      "symbols": ""
    },
    {
      "name": "زيد بْن بكر بْن خنيس",
      "symbols": ""
    },
    {
      "name": "سفيان الثوري",
      "symbols": "(د)"
    },
    {
      "name": "سُلَيْمان التَّيْمِيّ",
      "symbols": ""
    },
    {
      "name": "أَبُو عاصم الضحاك بْن مخلد النبيل",
      "symbols": "(بخ)"
    },
    {
      "name": "العباس بْن بكار الضبي",
      "symbols": ""
    },
    {
      "name": "عَبْد اللَّهِ بْن بَكْر السهمي",
      "symbols": ""
    },
    {
      "name": "عبد الله بْن شوذب",
      "symbols": "(ق)"
    },
    {
      "name": "عَبْد اللَّهِ بْن عون",
      "symbols": ""
    },
    {
      "name": "عبد القاهر بْن شعيب بْن الحبحاب",
      "symbols": ""
    },
    {
      "name": "أَبُو عُبَيدة عبد الْوَاحِدِ بْن واصل الحداد",
      "symbols": "(س)"
    },
    {
      "name": "عبد الوارث بْن سَعِيد",
      "symbols": ""
    },
    {
      "name": "عبد الوهاب بْن عطاء الخفاف",
      "symbols": ""
    },
    {
      "name": "عتاب بن المثنى",
      "symbols": "(ت)"
    },
    {
      "name": "علي بْن الْفَضْل",
      "symbols": ""
    },
    {
      "name": "علي بْن الربيع",
      "symbols": ""
    },
    {
      "name": "علي بْن عاصم الواسطي",
      "symbols": ""
    },
    {
      "name": "علي بْن غراب",
      "symbols": ""
    },
    {
      "name": "علي بْن مسعدة الباهلي",
      "symbols": ""
    },
    {
      "name": "عنبسة بْن عَبْد الواحد القرشي",
      "symbols": ""
    },
    {
      "name": "عيسى بْن يونس",
      "symbols": ""
    },
    {
      "name": "محمد بْن عَبْد اللَّهِ الأَنْصارِيّ",
      "symbols": ""
    },
    {
      "name": "محمد بْن أَبي عَدِيّ",
      "symbols": "(د)"
    },
    {
      "name": "محمد بْن عيسى ابن إسماعيل",
      "symbols": ""
    },
    {
      "name": "محمد بْن مسلم بْن شهاب الزُّهْرِيّ",
      "symbols": ""
    },
    {
      "name": "مخارق بْن الحارث الشيرازي",
      "symbols": ""
    },
    {
      "name": "مخيس بْن تميم الأشجعي",
      "symbols": ""
    },
    {
      "name": "مروان بْن معاوية الفزاري",
      "symbols": "(د)"
    },
    {
      "name": "مسعدة بْن اليسع",
      "symbols": ""
    },
    {
      "name": "مسلمة بْن قعنب الحارثي",
      "symbols": "(د)"
    },
    {
      "name": "معاذ بْن معاذ",
      "symbols": "(ت)"
    },
    {
      "name": "معتمر بْن سُلَيْمان",
      "symbols": "(س)"
    },
    {
      "name": "مَعْمَر بْن راشِد",
      "symbols": "(د س ق)"
    },
    {
      "name": "مكي بْن إِبْرَاهِيم البلخي",
      "symbols": "(عخ ت)"
    },
    {
      "name": "النضر بْن شميل",
      "symbols": "(ق)"
    },
    {
      "name": "هشام بْن حسان",
      "symbols": ""
    },
    {
      "name": "يحيى بْن سَعِيد القطان",
      "symbols": "(د ت س •)"
    },
    {
      "name": "يزيد بْن هارون",
      "symbols": "(د ت ق)"
    },
    {
      "name": "يوسف بْن يعقوب السدوسي",
      "symbols": "(ت)"
    },
    {
      "name": "أَبُو بَكْر الهذلي",
      "symbols": ""
    },
    {
      "name": "أَبُو حبيب القنوي",
      "symbols": ""
    }
  ]
}